Metadata-Version: 2.1
Name: tiff-wsi-label-removal
Version: 0.1.6
Summary: A tool to remove label pages from TIFF/BigTIFF files...
Home-page: https://github.com/zenquiorra/tiff-wsi-label-removal
Author: Yash Verma
Author-email: yashv7523@gmail.com
License: MIT
Classifier: Programming Language :: Python :: 3
Classifier: License :: OSI Approved :: MIT License
Classifier: Operating System :: OS Independent
Requires-Python: >=3.7
License-File: LICENSE
Requires-Dist: tifffile>=2023.4.12
